{
    "type": "create:mixing",
    "ingredients": [
      {
        "tag": "minecraft:flowers"
      },
      {
        "tag": "minecraft:flowers"
      },
      {
        "mixtureFluidWithTaggedMolecules": "destroy:mixture",
        "tag": "destroy:fragrant",
        "amount": 50,
        "concentration": 0.2
      },
      {
        "fluid": "minecraft:water",
        "amount": 200 
      }
    ],
    "results": [
      {
        "fluid": "destroy:perfume",
        "amount": 250
      }
    ]
  }